setup.py
strprint/__init__.py
strprint/libstr_print_c_warpper.so
strprint.egg-info/PKG-INFO
strprint.egg-info/SOURCES.txt
strprint.egg-info/dependency_links.txt
strprint.egg-info/top_level.txt