Metadata-Version: 2.1
Name: strprint
Version: 1.0.1
Summary: str print
Author: lixianyang
License: UNKNOWN
Platform: UNKNOWN
